{
  "name": "user",
  "plural": "users",
  "base": "PersistedModel",
  "idInjection": true,
  "options": {
    "validateUpsert": true
  },
  "properties": {
    "Name": {
      "type": "string",
      "required": true
    },
    "email": {
      "type": "string",
      "required": true
    },
    "contactNumber": {
      "type": "number",
      "required": true
    },
    "location":{
      "type":"object",
      "required":true
    }
  },
  "validations": [],
  "relations": {
    "foodOrders":{
      "type": "hasMany",
      "model": "foorOrders",
      "foreignKey": ""
    }
  },
  "acls": [],
  "methods": {}
}
